civic_lib_geo/__init__.py
civic_lib_geo/__main__.py
civic_lib_geo/_version.py
civic_lib_geo/fips_utils.py
civic_lib_geo/geojson_utils.py
civic_lib_geo/geometry.py
civic_lib_geo/py.typed
civic_lib_geo/shapefile_utils.py
civic_lib_geo/topojson_utils.py
civic_lib_geo/transform.py
civic_lib_geo/us_constants.py
civic_lib_geo/cli/__init__.py
civic_lib_geo/cli/check_size.py
civic_lib_geo/cli/chunk_geojson.py
civic_lib_geo/cli/cli.py
civic_lib_geo/cli/read_props.py
civic_lib_geo/cli/shapefile_to_geojson.py
civic_lib_geo/cli/simplify_geojson.py
civic_lib_geo/cli/topojson_to_geojson.py
civic_lib_geo-0.4.0.dist-info/licenses/LICENSE
civic_lib_geo-0.4.0.dist-info/METADATA
civic_lib_geo-0.4.0.dist-info/WHEEL
civic_lib_geo-0.4.0.dist-info/entry_points.txt
civic_lib_geo-0.4.0.dist-info/top_level.txt
civic_lib_geo-0.4.0.dist-info/RECORD
